{
  "type": "excalidraw/clipboard",
  "elements": [
    {
      "id": "XWbt6QCCE7NaM9LJ6VOXs",
      "type": "text",
      "x": 1650.186612734572,
      "y": 304.2489416392657,
      "width": 539.423828125,
      "height": 782,
      "angle": 0,
      "strokeColor": "#1e1e1e",
      "backgroundColor": "transparent",
      "fillStyle": "hachure",
      "strokeWidth": 2,
      "strokeStyle": "solid",
      "roughness": 0,
      "opacity": 100,
      "groupIds": [],
      "frameId": null,
      "index": "bJU",
      "roundness": null,
      "seed": 102969332,
      "version": 38,
      "versionNonce": 888372044,
      "isDeleted": false,
      "boundElements": null,
      "updated": 1721394867776,
      "link": null,
      "locked": false,
      "text": "{\n  \"view\": 0,\n  \"read\": true,\n  \"entries\": {\n      \"id\": \"35509196741702656\",\n      \"title\": \"在 Nest.js 中使用 Auth.js\",\n      \"url\": \"https://innei.in/posts/tech/using-auth-js-in-nestjs\",\n      \"guid\": \"https://innei.in/posts/tech/using-auth-js-in-nestjs\",\n      \"author\": \"Innei\",\n      \"authorUrl\": null,\n      \"authorAvatar\": null,\n      \"changedAt\": \"2024-07-15T03:04:27.227Z\",\n      \"publishedAt\": \"2024-07-14T06:45:25.000Z\",\n      \"images\": null,\n      \"categories\": null,\n      \"enclosures\": null,\n  },\n  \"feeds\": {\n      \"id\": \"33834308749487164\",\n      \"url\": \"http://innei.in/feed\",\n      \"title\": \"静かな森\",\n      \"description\": \"致虚极，守静笃。\",\n      \"siteUrl\": \"https://innei.in/\",\n      \"image\": \"https://innei.in/innei.svg\",\n      \"checkedAt\": \"2024-07-17T17:10:42.128Z\",\n      \"lastModifiedHeader\": \"Wed, 17 Jul 2024 04:52:30 GMT\",\n      \"etagHeader\": null,\n      \"ttl\": 60,\n      \"errorMessage\": null,\n      \"errorAt\": null,\n      \"ownerUserId\": null\n  },\n  \"collections\": null,\n}",
      "fontSize": 20,
      "fontFamily": 2,
      "textAlign": "left",
      "verticalAlign": "top",
      "containerId": null,
      "originalText": "{\n  \"view\": 0,\n  \"read\": true,\n  \"entries\": {\n      \"id\": \"35509196741702656\",\n      \"title\": \"在 Nest.js 中使用 Auth.js\",\n      \"url\": \"https://innei.in/posts/tech/using-auth-js-in-nestjs\",\n      \"guid\": \"https://innei.in/posts/tech/using-auth-js-in-nestjs\",\n      \"author\": \"Innei\",\n      \"authorUrl\": null,\n      \"authorAvatar\": null,\n      \"changedAt\": \"2024-07-15T03:04:27.227Z\",\n      \"publishedAt\": \"2024-07-14T06:45:25.000Z\",\n      \"images\": null,\n      \"categories\": null,\n      \"enclosures\": null,\n  },\n  \"feeds\": {\n      \"id\": \"33834308749487164\",\n      \"url\": \"http://innei.in/feed\",\n      \"title\": \"静かな森\",\n      \"description\": \"致虚极，守静笃。\",\n      \"siteUrl\": \"https://innei.in/\",\n      \"image\": \"https://innei.in/innei.svg\",\n      \"checkedAt\": \"2024-07-17T17:10:42.128Z\",\n      \"lastModifiedHeader\": \"Wed, 17 Jul 2024 04:52:30 GMT\",\n      \"etagHeader\": null,\n      \"ttl\": 60,\n      \"errorMessage\": null,\n      \"errorAt\": null,\n      \"ownerUserId\": null\n  },\n  \"collections\": null,\n}",
      "autoResize": true,
      "lineHeight": 1.15
    },
    {
      "id": "MEp73VsH1d4_7QZJPxqPB",
      "type": "text",
      "x": 2303.4977849300903,
      "y": 243.4863946382759,
      "width": 1118.740234375,
      "height": 920,
      "angle": 0,
      "strokeColor": "#1e1e1e",
      "backgroundColor": "transparent",
      "fillStyle": "hachure",
      "strokeWidth": 2,
      "strokeStyle": "solid",
      "roughness": 0,
      "opacity": 100,
      "groupIds": [],
      "frameId": null,
      "index": "bJV",
      "roundness": null,
      "seed": 2108529524,
      "version": 68,
      "versionNonce": 1719683020,
      "isDeleted": false,
      "boundElements": null,
      "updated": 1721394869426,
      "link": null,
      "locked": false,
      "text": "\n    \"code\": 0,\n    \"data\": [\n        {\n            \"read\": true,\n            \"view\": 0,\n            \"entries\": {\n                \"id\": \"35509196741702656\",\n                \"title\": \"在 Nest.js 中使用 Auth.js\",\n                \"url\": \"https://innei.in/posts/tech/using-auth-js-in-nestjs\",\n                \"description\": \"当前内容无法在 RSS render 中正确渲染，请前往：$https://innei.in/posts/tech/using-auth-js-in-nestjs\",\n                \"guid\": \"https://innei.in/posts/tech/using-auth-js-in-nestjs\",\n                \"author\": \"Innei\",\n                \"authorUrl\": null,\n                \"authorAvatar\": null,\n                \"changedAt\": \"2024-07-15T03:04:27.227Z\",\n                \"publishedAt\": \"2024-07-14T06:45:25.000Z\",\n                \"images\": null,\n                \"categories\": null,\n                \"enclosures\": null\n            },\n            \"feeds\": {\n                \"id\": \"33834308749487164\",\n                \"url\": \"http://innei.in/feed\",\n                \"title\": \"静かな森\",\n                \"description\": \"致虚极，守静笃。\",\n                \"siteUrl\": \"https://innei.in/\",\n                \"image\": \"https://innei.in/innei.svg\",\n                \"checkedAt\": \"2024-07-17T17:10:42.128Z\",\n                \"lastModifiedHeader\": \"Wed, 17 Jul 2024 04:52:30 GMT\",\n                \"etagHeader\": null,\n                \"ttl\": 60,\n                \"errorMessage\": null,\n                \"errorAt\": null,\n                \"ownerUserId\": null\n            },\n            \"collections\": null,\n            \"settings\": {}\n        },\n}",
      "fontSize": 20,
      "fontFamily": 2,
      "textAlign": "left",
      "verticalAlign": "top",
      "containerId": null,
      "originalText": "\n    \"code\": 0,\n    \"data\": [\n        {\n            \"read\": true,\n            \"view\": 0,\n            \"entries\": {\n                \"id\": \"35509196741702656\",\n                \"title\": \"在 Nest.js 中使用 Auth.js\",\n                \"url\": \"https://innei.in/posts/tech/using-auth-js-in-nestjs\",\n                \"description\": \"当前内容无法在 RSS render 中正确渲染，请前往：$https://innei.in/posts/tech/using-auth-js-in-nestjs\",\n                \"guid\": \"https://innei.in/posts/tech/using-auth-js-in-nestjs\",\n                \"author\": \"Innei\",\n                \"authorUrl\": null,\n                \"authorAvatar\": null,\n                \"changedAt\": \"2024-07-15T03:04:27.227Z\",\n                \"publishedAt\": \"2024-07-14T06:45:25.000Z\",\n                \"images\": null,\n                \"categories\": null,\n                \"enclosures\": null\n            },\n            \"feeds\": {\n                \"id\": \"33834308749487164\",\n                \"url\": \"http://innei.in/feed\",\n                \"title\": \"静かな森\",\n                \"description\": \"致虚极，守静笃。\",\n                \"siteUrl\": \"https://innei.in/\",\n                \"image\": \"https://innei.in/innei.svg\",\n                \"checkedAt\": \"2024-07-17T17:10:42.128Z\",\n                \"lastModifiedHeader\": \"Wed, 17 Jul 2024 04:52:30 GMT\",\n                \"etagHeader\": null,\n                \"ttl\": 60,\n                \"errorMessage\": null,\n                \"errorAt\": null,\n                \"ownerUserId\": null\n            },\n            \"collections\": null,\n            \"settings\": {}\n        },\n}",
      "autoResize": true,
      "lineHeight": 1.15
    },
    {
      "id": "jfjXcRlGzpSLEVqJJHegq",
      "type": "rectangle",
      "x": 1606.2887343505838,
      "y": 377.8265721107703,
      "width": 596.7014442613197,
      "height": 312.474999408672,
      "angle": 0,
      "strokeColor": "#e03131",
      "backgroundColor": "transparent",
      "fillStyle": "hachure",
      "strokeWidth": 2,
      "strokeStyle": "solid",
      "roughness": 0,
      "opacity": 100,
      "groupIds": [],
      "frameId": null,
      "index": "bJW",
      "roundness": null,
      "seed": 1452393676,
      "version": 63,
      "versionNonce": 1922000844,
      "isDeleted": false,
      "boundElements": [
        {
          "id": "V15zXxv8NMAoJ2ddMe_j-",
          "type": "arrow"
        }
      ],
      "updated": 1721394998988,
      "link": null,
      "locked": false
    },
    {
      "id": "4BqUMiKZDeJuZvk4QVvDE",
      "type": "rectangle",
      "x": 2333.45439162206,
      "y": 380.571655900683,
      "width": 914.3709868416727,
      "height": 336.27980294068357,
      "angle": 0,
      "strokeColor": "#e03131",
      "backgroundColor": "transparent",
      "fillStyle": "hachure",
      "strokeWidth": 2,
      "strokeStyle": "solid",
      "roughness": 0,
      "opacity": 100,
      "groupIds": [],
      "frameId": null,
      "index": "bJX",
      "roundness": null,
      "seed": 2013706228,
      "version": 53,
      "versionNonce": 1023961676,
      "isDeleted": false,
      "boundElements": [
        {
          "id": "zC-YL2sj0tYwPfroxvzM6",
          "type": "arrow"
        }
      ],
      "updated": 1721395000240,
      "link": null,
      "locked": false
    },
    {
      "id": "VEHH6paG4OVS8iFxf0x_t",
      "type": "text",
      "x": 2218.53157606864,
      "y": 510.52439176023995,
      "width": 101.15234375,
      "height": 23,
      "angle": 0,
      "strokeColor": "#e03131",
      "backgroundColor": "transparent",
      "fillStyle": "hachure",
      "strokeWidth": 2,
      "strokeStyle": "solid",
      "roughness": 0,
      "opacity": 100,
      "groupIds": [],
      "frameId": null,
      "index": "bJY",
      "roundness": null,
      "seed": 378791412,
      "version": 27,
      "versionNonce": 241545932,
      "isDeleted": false,
      "boundElements": null,
      "updated": 1721394891209,
      "link": null,
      "locked": false,
      "text": "EntryModel",
      "fontSize": 20,
      "fontFamily": 2,
      "textAlign": "left",
      "verticalAlign": "top",
      "containerId": null,
      "originalText": "EntryModel",
      "autoResize": true,
      "lineHeight": 1.15
    },
    {
      "id": "mvluGX9D4JNeNXNpjrOtR",
      "type": "rectangle",
      "x": 1626.1190319508762,
      "y": 699.9539430679042,
      "width": 547.6090227056511,
      "height": 349.0995788621219,
      "angle": 0,
      "strokeColor": "#1971c2",
      "backgroundColor": "transparent",
      "fillStyle": "hachure",
      "strokeWidth": 2,
      "strokeStyle": "solid",
      "roughness": 0,
      "opacity": 100,
      "groupIds": [],
      "frameId": null,
      "index": "bJZ",
      "roundness": null,
      "seed": 1314418636,
      "version": 70,
      "versionNonce": 1546254540,
      "isDeleted": false,
      "boundElements": [
        {
          "id": "v2lgeXZJEvvA-M6gdXJSM",
          "type": "arrow"
        }
      ],
      "updated": 1721395006291,
      "link": null,
      "locked": false
    },
    {
      "type": "rectangle",
      "version": 132,
      "versionNonce": 1591835084,
      "index": "bJa",
      "isDeleted": false,
      "id": "lPnrpkBRevMV7cNIW8BRa",
      "fillStyle": "hachure",
      "strokeWidth": 2,
      "strokeStyle": "solid",
      "roughness": 0,
      "opacity": 100,
      "angle": 0,
      "x": 2340.6666886905996,
      "y": 728.6623578143756,
      "strokeColor": "#1971c2",
      "backgroundColor": "transparent",
      "width": 547.6090227056511,
      "height": 349.0995788621219,
      "seed": 731432652,
      "groupIds": [],
      "frameId": null,
      "roundness": null,
      "boundElements": [
        {
          "id": "s5-OWqtSKMxQkUS6GBJxH",
          "type": "arrow"
        }
      ],
      "updated": 1721395008106,
      "link": null,
      "locked": false
    },
    {
      "id": "jYdp1-jlx9tHQpNFPwMth",
      "type": "text",
      "x": 2208.189414234507,
      "y": 857.6109091764258,
      "width": 100.05859375,
      "height": 23,
      "angle": 0,
      "strokeColor": "#1971c2",
      "backgroundColor": "transparent",
      "fillStyle": "hachure",
      "strokeWidth": 2,
      "strokeStyle": "solid",
      "roughness": 0,
      "opacity": 100,
      "groupIds": [],
      "frameId": null,
      "index": "bJb",
      "roundness": null,
      "seed": 2018732492,
      "version": 28,
      "versionNonce": 257962740,
      "isDeleted": false,
      "boundElements": null,
      "updated": 1721394920560,
      "link": null,
      "locked": false,
      "text": "FeedModel",
      "fontSize": 20,
      "fontFamily": 2,
      "textAlign": "left",
      "verticalAlign": "top",
      "containerId": null,
      "originalText": "FeedModel",
      "autoResize": true,
      "lineHeight": 1.15
    },
    {
      "id": "N-vZ7Y3lZwVfIXh_Xs3iS",
      "type": "rectangle",
      "x": 1817.281222886605,
      "y": -23.851913773214164,
      "width": 879.5828403222545,
      "height": 248.66273388187994,
      "angle": 0,
      "strokeColor": "#1e1e1e",
      "backgroundColor": "transparent",
      "fillStyle": "hachure",
      "strokeWidth": 2,
      "strokeStyle": "solid",
      "roughness": 0,
      "opacity": 100,
      "groupIds": [],
      "frameId": null,
      "index": "bJc",
      "roundness": {
        "type": 3
      },
      "seed": 874593100,
      "version": 66,
      "versionNonce": 780391628,
      "isDeleted": false,
      "boundElements": null,
      "updated": 1721394981377,
      "link": null,
      "locked": false
    },
    {
      "id": "7VAEyvGfDptXUfSDp7pWg",
      "type": "rectangle",
      "x": 1911.2549272194613,
      "y": 32.707302871608704,
      "width": 184.98962888152866,
      "height": 122.7240846787953,
      "angle": 0,
      "strokeColor": "#1e1e1e",
      "backgroundColor": "transparent",
      "fillStyle": "hachure",
      "strokeWidth": 2,
      "strokeStyle": "solid",
      "roughness": 0,
      "opacity": 100,
      "groupIds": [],
      "frameId": null,
      "index": "bJd",
      "roundness": null,
      "seed": 786243444,
      "version": 42,
      "versionNonce": 1078146508,
      "isDeleted": false,
      "boundElements": [
        {
          "type": "text",
          "id": "vRb2m7JNHP4FQ92qiWhD9"
        },
        {
          "id": "v2lgeXZJEvvA-M6gdXJSM",
          "type": "arrow"
        }
      ],
      "updated": 1721395006291,
      "link": null,
      "locked": false
    },
    {
      "id": "vRb2m7JNHP4FQ92qiWhD9",
      "type": "text",
      "x": 1954.3397914038778,
      "y": 81.56934521100635,
      "width": 98.81990051269531,
      "height": 25,
      "angle": 0,
      "strokeColor": "#1e1e1e",
      "backgroundColor": "transparent",
      "fillStyle": "hachure",
      "strokeWidth": 2,
      "strokeStyle": "solid",
      "roughness": 0,
      "opacity": 100,
      "groupIds": [],
      "frameId": null,
      "index": "bJdV",
      "roundness": null,
      "seed": 69424500,
      "version": 13,
      "versionNonce": 924326348,
      "isDeleted": false,
      "boundElements": null,
      "updated": 1721394963885,
      "link": null,
      "locked": false,
      "text": "FeedStore",
      "fontSize": 20,
      "fontFamily": 1,
      "textAlign": "center",
      "verticalAlign": "middle",
      "containerId": "7VAEyvGfDptXUfSDp7pWg",
      "originalText": "FeedStore",
      "autoResize": true,
      "lineHeight": 1.25
    },
    {
      "type": "rectangle",
      "version": 59,
      "versionNonce": 374556492,
      "index": "bJn",
      "isDeleted": false,
      "id": "D4sE-7rWFIGlK-I_SvzPs",
      "fillStyle": "hachure",
      "strokeWidth": 2,
      "strokeStyle": "solid",
      "roughness": 0,
      "opacity": 100,
      "angle": 0,
      "x": 2162.281031764909,
      "y": 28.45608884096538,
      "strokeColor": "#1e1e1e",
      "backgroundColor": "transparent",
      "width": 184.98962888152866,
      "height": 122.7240846787953,
      "seed": 155636684,
      "groupIds": [],
      "frameId": null,
      "roundness": null,
      "boundElements": [
        {
          "type": "text",
          "id": "ZzRZj_O-yClNNXB1oCst3"
        },
        {
          "id": "V15zXxv8NMAoJ2ddMe_j-",
          "type": "arrow"
        },
        {
          "id": "zC-YL2sj0tYwPfroxvzM6",
          "type": "arrow"
        }
      ],
      "updated": 1721395000240,
      "link": null,
      "locked": false
    },
    {
      "type": "text",
      "version": 39,
      "versionNonce": 1745568844,
      "index": "bJo",
      "isDeleted": false,
      "id": "ZzRZj_O-yClNNXB1oCst3",
      "fillStyle": "hachure",
      "strokeWidth": 2,
      "strokeStyle": "solid",
      "roughness": 0,
      "opacity": 100,
      "angle": 0,
      "x": 2201.68589564415,
      "y": 77.31813118036303,
      "strokeColor": "#1e1e1e",
      "backgroundColor": "transparent",
      "width": 106.17990112304688,
      "height": 25,
      "seed": 726825548,
      "groupIds": [],
      "frameId": null,
      "roundness": null,
      "boundElements": [],
      "updated": 1721394996833,
      "link": null,
      "locked": false,
      "fontSize": 20,
      "fontFamily": 1,
      "text": "EntryStore",
      "textAlign": "center",
      "verticalAlign": "middle",
      "containerId": "D4sE-7rWFIGlK-I_SvzPs",
      "originalText": "EntryStore",
      "autoResize": true,
      "lineHeight": 1.25
    },
    {
      "type": "rectangle",
      "version": 74,
      "versionNonce": 1465426380,
      "index": "bJp",
      "isDeleted": false,
      "id": "FfdH34jdWMF44dVdGxU2Y",
      "fillStyle": "hachure",
      "strokeWidth": 2,
      "strokeStyle": "solid",
      "roughness": 0,
      "opacity": 100,
      "angle": 0,
      "x": 2415.1854691315025,
      "y": 32.650239596029735,
      "strokeColor": "#1e1e1e",
      "backgroundColor": "transparent",
      "width": 184.98962888152866,
      "height": 122.7240846787953,
      "seed": 244094156,
      "groupIds": [],
      "frameId": null,
      "roundness": null,
      "boundElements": [
        {
          "type": "text",
          "id": "v0TJd8cGdNNA0PZyhsyHu"
        }
      ],
      "updated": 1721394973494,
      "link": null,
      "locked": false
    },
    {
      "type": "text",
      "version": 61,
      "versionNonce": 1963122508,
      "index": "bJq",
      "isDeleted": false,
      "id": "v0TJd8cGdNNA0PZyhsyHu",
      "fillStyle": "hachure",
      "strokeWidth": 2,
      "strokeStyle": "solid",
      "roughness": 0,
      "opacity": 100,
      "angle": 0,
      "x": 2486.0603037138685,
      "y": 81.51228193542738,
      "strokeColor": "#1e1e1e",
      "backgroundColor": "transparent",
      "width": 43.239959716796875,
      "height": 25,
      "seed": 1681398604,
      "groupIds": [],
      "frameId": null,
      "roundness": null,
      "boundElements": [],
      "updated": 1721394974823,
      "link": null,
      "locked": false,
      "fontSize": 20,
      "fontFamily": 1,
      "text": "etc..",
      "textAlign": "center",
      "verticalAlign": "middle",
      "containerId": "FfdH34jdWMF44dVdGxU2Y",
      "originalText": "etc..",
      "autoResize": true,
      "lineHeight": 1.25
    },
    {
      "id": "Qh_OHI6KGo0pDlq43wT7D",
      "type": "text",
      "x": 2200.1282492927508,
      "y": -77.13440829996534,
      "width": 97.34397888183594,
      "height": 45,
      "angle": 0,
      "strokeColor": "#1e1e1e",
      "backgroundColor": "transparent",
      "fillStyle": "hachure",
      "strokeWidth": 2,
      "strokeStyle": "solid",
      "roughness": 0,
      "opacity": 100,
      "groupIds": [],
      "frameId": null,
      "index": "bJt",
      "roundness": null,
      "seed": 1005047668,
      "version": 41,
      "versionNonce": 1406279500,
      "isDeleted": false,
      "boundElements": null,
      "updated": 1721394989210,
      "link": null,
      "locked": false,
      "text": "Store",
      "fontSize": 36,
      "fontFamily": 1,
      "textAlign": "left",
      "verticalAlign": "top",
      "containerId": null,
      "originalText": "Store",
      "autoResize": true,
      "lineHeight": 1.25
    },
    {
      "id": "V15zXxv8NMAoJ2ddMe_j-",
      "type": "arrow",
      "x": 2009.6225037719084,
      "y": 388.8487163067331,
      "width": 206.25520958067523,
      "height": 228.69058742919322,
      "angle": 0,
      "strokeColor": "#1e1e1e",
      "backgroundColor": "transparent",
      "fillStyle": "hachure",
      "strokeWidth": 2,
      "strokeStyle": "solid",
      "roughness": 0,
      "opacity": 100,
      "groupIds": [],
      "frameId": null,
      "index": "bJv",
      "roundness": null,
      "seed": 154458828,
      "version": 36,
      "versionNonce": 107515468,
      "isDeleted": false,
      "boundElements": null,
      "updated": 1721394998988,
      "link": null,
      "locked": false,
      "points": [
        [
          0,
          0
        ],
        [
          206.25520958067523,
          -228.69058742919322
        ]
      ],
      "lastCommittedPoint": null,
      "startBinding": {
        "elementId": "jfjXcRlGzpSLEVqJJHegq",
        "focus": -0.05915883383210289,
        "gap": 1
      },
      "endBinding": {
        "elementId": "D4sE-7rWFIGlK-I_SvzPs",
        "focus": -0.16600210040616112,
        "gap": 8.977955357779194
      },
      "startArrowhead": null,
      "endArrowhead": "arrow"
    },
    {
      "id": "zC-YL2sj0tYwPfroxvzM6",
      "type": "arrow",
      "x": 2395.7126263401333,
      "y": 385.10156121037187,
      "width": 131.93029313889065,
      "height": 226.65533060020516,
      "angle": 0,
      "strokeColor": "#1e1e1e",
      "backgroundColor": "transparent",
      "fillStyle": "hachure",
      "strokeWidth": 2,
      "strokeStyle": "solid",
      "roughness": 0,
      "opacity": 100,
      "groupIds": [],
      "frameId": null,
      "index": "bJw",
      "roundness": null,
      "seed": 419064652,
      "version": 24,
      "versionNonce": 1335705804,
      "isDeleted": false,
      "boundElements": null,
      "updated": 1721395000240,
      "link": null,
      "locked": false,
      "points": [
        [
          0,
          0
        ],
        [
          -131.93029313889065,
          -226.65533060020516
        ]
      ],
      "lastCommittedPoint": null,
      "startBinding": {
        "elementId": "4BqUMiKZDeJuZvk4QVvDE",
        "focus": -0.5399353353515145,
        "gap": 1
      },
      "endBinding": {
        "elementId": "D4sE-7rWFIGlK-I_SvzPs",
        "focus": 0.24132029773631022,
        "gap": 7.266057090406036
      },
      "startArrowhead": null,
      "endArrowhead": "arrow"
    },
    {
      "id": "v2lgeXZJEvvA-M6gdXJSM",
      "type": "arrow",
      "x": 2191.768479420412,
      "y": 766.6931955537768,
      "width": 154.83168773797183,
      "height": 604.7756156792146,
      "angle": 0,
      "strokeColor": "#1e1e1e",
      "backgroundColor": "transparent",
      "fillStyle": "hachure",
      "strokeWidth": 2,
      "strokeStyle": "solid",
      "roughness": 0,
      "opacity": 100,
      "groupIds": [],
      "frameId": null,
      "index": "bJx",
      "roundness": null,
      "seed": 1434746316,
      "version": 48,
      "versionNonce": 1619590988,
      "isDeleted": false,
      "boundElements": null,
      "updated": 1721395006291,
      "link": null,
      "locked": false,
      "points": [
        [
          0,
          0
        ],
        [
          -154.83168773797183,
          -604.7756156792146
        ]
      ],
      "lastCommittedPoint": null,
      "startBinding": {
        "elementId": "mvluGX9D4JNeNXNpjrOtR",
        "focus": 1.0029958959910226,
        "gap": 18.04042476388497
      },
      "endBinding": {
        "elementId": "7VAEyvGfDptXUfSDp7pWg",
        "focus": -0.14617588754888863,
        "gap": 6.486192324158196
      },
      "startArrowhead": null,
      "endArrowhead": "arrow"
    },
    {
      "id": "s5-OWqtSKMxQkUS6GBJxH",
      "type": "arrow",
      "x": 2354.722173382476,
      "y": 799.076604444919,
      "width": 296.78609628692493,
      "height": 615.979038784579,
      "angle": 0,
      "strokeColor": "#1e1e1e",
      "backgroundColor": "transparent",
      "fillStyle": "hachure",
      "strokeWidth": 2,
      "strokeStyle": "solid",
      "roughness": 0,
      "opacity": 100,
      "groupIds": [],
      "frameId": null,
      "index": "bJy",
      "roundness": null,
      "seed": 1215470668,
      "version": 40,
      "versionNonce": 1721746252,
      "isDeleted": false,
      "boundElements": null,
      "updated": 1721395008106,
      "link": null,
      "locked": false,
      "points": [
        [
          0,
          0
        ],
        [
          -296.78609628692493,
          -615.979038784579
        ]
      ],
      "lastCommittedPoint": null,
      "startBinding": {
        "elementId": "lPnrpkBRevMV7cNIW8BRa",
        "focus": -0.5855616718959223,
        "gap": 1
      },
      "endBinding": null,
      "startArrowhead": null,
      "endArrowhead": "arrow"
    }
  ],
  "files": {}
}